hdns/__init__.py
hdns/arecords.py
hdns/ipv4.py
hdns-0.7.dist-info/METADATA
hdns-0.7.dist-info/WHEEL
hdns-0.7.dist-info/top_level.txt
hdns-0.7.dist-info/RECORD
