Metadata-Version: 2.1
Name: hdns
Version: 0.7
Summary: A simple library to handle Hetzner DNS API
Home-page: https://github.com/yourusername/your_package_name
Author: shadi andrew
License: UNKNOWN
Platform: UNKNOWN
Classifier: Programming Language :: Python :: 3
Classifier: License :: OSI Approved :: MIT License
Classifier: Operating System :: OS Independent
